turkish_profile_generator/UserProfileGenerator.py
turkish_profile_generator/__init__.py
turkish_profile_generator/data/firstname_female.txt
turkish_profile_generator/data/firstname_male.txt
turkish_profile_generator/data/firstname_uni.txt
turkish_profile_generator/data/lastname.txt
turkish_profile_generator-0.2.1.dist-info/LICENSE
turkish_profile_generator-0.2.1.dist-info/METADATA
turkish_profile_generator-0.2.1.dist-info/WHEEL
turkish_profile_generator-0.2.1.dist-info/top_level.txt
turkish_profile_generator-0.2.1.dist-info/RECORD
