Metadata-Version: 2.1
Name: turkish-profile-generator
Version: 0.2.1
Summary: Example PyPI (Python Package Index) Package
Home-page: https://github.com/bossturk/turkish-profile-generator
Author: Mustafa Buyruk
Author-email: bossturk@hotmail.com
Project-URL: Documentation, https://github.com/bossturk/turkish-profile-generator
Project-URL: Bug Reports, https://github.com/bossturk/turkish-profile-generator/issues
Project-URL: Source Code, https://github.com/bossturk/turkish-profile-generator
Keywords: example,pypi,package
Classifier: Development Status :: 5 - Production/Stable
Classifier: Intended Audience :: Developers
Classifier: Topic :: Software Development :: Build Tools
Classifier: Programming Language :: Python :: 3
Classifier: Programming Language :: Python :: 3.6
Classifier: Programming Language :: Python :: 3.7
Classifier: Programming Language :: Python :: 3.8
Classifier: Programming Language :: Python :: 3.9
Classifier: Programming Language :: Python :: 3 :: Only
Classifier: License :: OSI Approved :: MIT License
Classifier: Operating System :: OS Independent
Requires-Python: >=3.6
License-File: LICENSE
Provides-Extra: dev
Requires-Dist: check-manifest ; extra == 'dev'
